[
  {
    "measurement": "local_mem",
    "data": {
      "used": 941813760.0,
      "free": 5515522048.0,
      "used_percent": 11.457445234124336,
      "total": 8220102656.0,
      "timestamp": "1750756791000000000"
    }
  },
  {
    "measurement": "local_system",
    "data": {
      "load1": 0.56,
      "uptime": null,
      "timestamp": "1750756791000000000"
    }
  },
  {
    "measurement": "local_system",
    "data": {
      "load1": null,
      "uptime": 5209.0,
      "timestamp": "1750756791000000000"
    }
  },
  {
    "measurement": "local_system",
    "data": {
      "load1": null,
      "uptime": null,
      "timestamp": "1:26\""
    }
  },
  {
    "measurement": "router_ping",
    "data": {
      "latency_ms": 38.121,
      "packet_loss": 0.0,
      "timestamp": "1750756791000000000"
    }
  },
  {
    "measurement": "router_snmp",
    "data": {
      "router_name": "pod4-cat8kv",
      "uptime": 172235241.0,
      "cpu_5min": 0.0,
      "timestamp": "1750756791000000000"
    }
  },
  {
    "measurement": "local_cpu",
    "data": {
      "usage_idle": 99.5012468828722,
      "usage_user": 0.24937655860359026,
      "usage_system": 0.24937655860359026,
      "timestamp": "1750756791000000000"
    }
  }
]